{
  "name": "Morning Ride",
  "type": "Ride",
  "distance_m": 30853,
  "moving_time_s": 4295,
  "total_elevation_gain_m": 286,
  "start_date_local": "2026-07-17T07:18:42Z",
  "summary_polyline": "g{ezEltspOy@l@?ZTfAEVuBhB{In@}@b@oDrCcBXcAEyIrA_AnAmCpA}ANsDOQd@sAlJYlCU`IBpC`@lFn@~BxChEvA~CdAhEPhBDlBApBc@fJO`A@bBcCjk@OdADnAYlW^dCx@lBnJlKn@bCFxBQ`BqAtGeB~Li@zM]vBu@xA{@v@qFbBiAp@aAnAo@nBW|CBhA_@dMUhFg@bHaApFyCvIqAtFUbCg@fKWL{BWkAc@r@`@~C^JLs@|KMFkA[eFmBmFz@oBG_A[Y_@W{@g@Q{@Hq@\\]l@S|@QhDXxA`A`CAt@YhANl@hG|KrA|AbCz@rG^F^I\\MHD@?TI|@SPyF}@{IaCiBoAqSoJuBq@yBYgBCyBPeB`@kBv@qDtC}@lAeAnBgCnGkCjIaQ|b@o@|CyAlE]|ADp@Sx@O`BaA~ON]TiBZU|Ll@NNqAvZ]d@{@LUP?lDQh@oGc@i@NQbD?pGUx@kAZO[oG~Ay@p@s@bAa@bASjAu@fL_Bh_@[xBeBnF@RRVhDfB`@f@Xp@TrApB|SBtA_@jAk@^aBXYb@x@xGb@@hRmD{@uJ@}D]sKi@O}@s@sA{BBg@Yu@M{@Bk@Zy@GWe@c@EeAJo@f@[d@q@bEu@v@s@|ADXy@nA_@n@HFlAPj@p@BRTk@lA|@dJvCHnBXrCCpJ`@^YvAcCb@{APyAOoCNk@zDkGvCgCv@_@|@kAlA_ArBnCpB|AnCh@dCIx@XR^v@rCjA`C`B~Bl@RpBbDpAzAp@|AhD`BhAp@tBYzCuBbAYHNjCuAvFyDv@?v@[lFiD|CcCtBiARHzBzF`@Kl@m@v@uB`@cI[AwFxD]DaCmGwAmDEaBeAw@_E}Kc@{@{@k@{HyBsB_AkQqLgA_AKg@vEsL`@cBhAiJr@sBrD_I^sAXuB|@ii@OkHyA}TDeBJIFyAQm@rD}e@fAuUXaDv@wD`DkJx@eEpAyQZwMVgCVsAv@}AbAaAhFcB`Ai@hAsAn@eBPkAb@sMnDuYEkCq@eCaAuAiH}H{@sB]{BXkWLaA?wBrBwg@XkDAyA`@iLY}Eg@yCiCkG}BgDq@yBYgEK}EPwF^aElAoINWfDNdBOrEyBx@y@vJ}@lAWx@g@xBsBz@a@hIe@n@[pAkAHu@MyALYb@W"
}
